yose/__init__.py
yose/clustering.py
yose/mpjoin.py
yose/screening.py
yose/subspace_wrd.py
yose/word2vec.py
yose-0.1.3.dist-info/licenses/LICENSE
yose-0.1.3.dist-info/METADATA
yose-0.1.3.dist-info/WHEEL
yose-0.1.3.dist-info/top_level.txt
yose-0.1.3.dist-info/RECORD
