Metadata-Version: 2.4
Name: yose
Version: 0.1.3
Home-page: https://github.com/m-dev672/yose
Author: Koutarou Mori
Author-email: m.koutarou2004@example.com
License: MIT
Classifier: Programming Language :: Python :: 3
Classifier: Operating System :: OS Independent
Classifier: Topic :: Scientific/Engineering :: Artificial Intelligence
Classifier: Topic :: Text Processing :: Linguistic
Requires-Python: >=3.8
License-File: LICENSE
Requires-Dist: numpy==1.26.4
Requires-Dist: scikit-learn==1.6.1
Requires-Dist: POT==0.9.5
Requires-Dist: jax==0.5.2
Requires-Dist: ott-jax==0.5.0
Dynamic: author
Dynamic: author-email
Dynamic: classifier
Dynamic: home-page
Dynamic: license
Dynamic: license-file
Dynamic: requires-dist
Dynamic: requires-python
